fusionsolar/__init__.py
fusionsolar/client.py
fusionsolar-0.0.6.dist-info/LICENSE
fusionsolar-0.0.6.dist-info/METADATA
fusionsolar-0.0.6.dist-info/WHEEL
fusionsolar-0.0.6.dist-info/top_level.txt
fusionsolar-0.0.6.dist-info/RECORD
