Metadata-Version: 2.1
Name: fusionsolar
Version: 0.0.6
Summary: A Python client for Huawei FusionSolar
Home-page: https://github.com/EnergieID/fusionsolar
Author: EnergieID.be
Author-email: jan@energieid.be
License: MIT
Keywords: Huawei PV Solar FusionSolar API Python
Platform: UNKNOWN
Classifier: Development Status :: 3 - Alpha
Classifier: Intended Audience :: Developers
Classifier: Topic :: Scientific/Engineering
Classifier: License :: OSI Approved :: MIT License
Classifier: Programming Language :: Python :: 3.6
Classifier: Programming Language :: Python :: 3.7
Requires-Dist: requests
Requires-Dist: pandas
